LICENSE.txt
README.md
setup.py
vasprocar/__init__.py
vasprocar/__main__.py
vasprocar.egg-info/PKG-INFO
vasprocar.egg-info/SOURCES.txt
vasprocar.egg-info/dependency_links.txt
vasprocar.egg-info/entry_points.txt
vasprocar.egg-info/requires.txt
vasprocar.egg-info/top_level.txt
vasprocar/src/_dft.py
vasprocar/src/_dft2kp.py
vasprocar/src/_loop.py
vasprocar/src/_samba.py
vasprocar/src/_settings.py
vasprocar/src/_update.py
vasprocar/src/bandas_2D.py
vasprocar/src/bandas_3D.py
vasprocar/src/bandas_4D.py
vasprocar/src/correction_file.py
vasprocar/src/fermi_surface.py
vasprocar/src/level_countour.py
vasprocar/src/orbital_texture.py
vasprocar/src/orbital_texture_vector.py
vasprocar/src/projecao_localizacao.py
vasprocar/src/projecao_orbitais.py
vasprocar/src/projecao_psi.py
vasprocar/src/projecao_spin.py
vasprocar/src/spin_texture.py
vasprocar/src/spin_texture_contour.py
vasprocar/src/spin_texture_contour_video.py
vasprocar/src/_QE/_info.py
vasprocar/src/_QE/_info_b.py
vasprocar/src/_QE/_label.py
vasprocar/src/_QE/_nscf.py
vasprocar/src/_QE/_var_kpoints.py
vasprocar/src/_QE/contribuicao.py
vasprocar/src/_QE/dos_pdos_ldos.py
vasprocar/src/_QE/kpoints_2D_3D.py
vasprocar/src/_QE/projecao_angular_momentum.py
vasprocar/src/_QE/angular_momentum_plot/plot_projecao_angular_momentum.py
vasprocar/src/_QE/angular_momentum_plot/plot_projecao_angular_momentum_grace.py
vasprocar/src/_QE/dos_plot/plot_dos_pdos_ldos.py
vasprocar/src/_QE/dos_plot/plot_dos_pdos_ldos_[polarizado].py
vasprocar/src/_QE/dos_plot/Grace/plot_dos_pdos_ldos.py
vasprocar/src/_QE/dos_plot/Grace/plot_dos_pdos_ldos_[polarizado].py
vasprocar/src/_QE/dos_plot/Grace/plot_dos_pdos_ldos_[polarizado_delta].py
vasprocar/src/_VASP/_info.py
vasprocar/src/_VASP/_info_b.py
vasprocar/src/_VASP/_label.py
vasprocar/src/_VASP/_nscf.py
vasprocar/src/_VASP/_var_kpoints.py
vasprocar/src/_VASP/chgcar.py
vasprocar/src/_VASP/contcar_info.py
vasprocar/src/_VASP/contribuicao.py
vasprocar/src/_VASP/dielectric_function.py
vasprocar/src/_VASP/dos_pdos_ldos.py
vasprocar/src/_VASP/dos_pdos_ldos_[polarizado].py
vasprocar/src/_VASP/kpoints_2D_3D.py
vasprocar/src/_VASP/parchg.py
vasprocar/src/_VASP/poscar_coord_conversion.py
