Metadata-Version: 2.1
Name: vasprocar
Version: 1.1.19.194
Summary: VASProcar is an open-source package written in the Python 3 programming language, which aims to provide an intuitive tool for the post-processing of the output files produced by the DFT VASP/QE codes, through an interactive user interface.
Home-page: https://doi.org/10.5281/zenodo.6343960
Download-URL: https://doi.org/10.5281/zenodo.6343960
Author: Augusto de Lelis Araujo and Renan da Paixao Maciel
Author-email: augusto-lelis@outlook.com, renan.maciel@physics.uu.se
License: GNU GPLv3
License-File: LICENSE.txt
Requires-Dist: numpy>=1.24.1
Requires-Dist: scipy>=1.10.0
Requires-Dist: matplotlib>=3.8.0
Requires-Dist: plotly>=5.13.0
Requires-Dist: moviepy>=1.0.2
Requires-Dist: kaleido>=0.2.1
Requires-Dist: requests>=2.31.0
